pixelart_tui/__init__.py
pixelart_tui/canvas.py
pixelart_tui/command_line.py
pixelart_tui/file_tools.py
pixelart_tui/main.py
pixelart_tui/my_button.py
pixelart_tui/my_messages.py
pixelart_tui/my_widgets.py
pixelart_tui-0.3.dist-info/LICENSE
pixelart_tui-0.3.dist-info/METADATA
pixelart_tui-0.3.dist-info/WHEEL
pixelart_tui-0.3.dist-info/entry_points.txt
pixelart_tui-0.3.dist-info/top_level.txt
pixelart_tui-0.3.dist-info/RECORD
