Metadata-Version: 2.1
Name: pixelart-tui
Version: 0.3
Summary: Terminal based app for Pixel Art that supports mouse!
Home-page: http://github.com/Cvaniak/PixelArtTUI
Author: Cvaniak
Author-email: igna.cwaniak@gmail.com
License: MIT
Platform: UNKNOWN
License-File: LICENSE
Requires-Dist: textual (==0.1.15)
Requires-Dist: textual-inputs (==0.2.5)
